[
  {
    "lat": 49.75828,
    "lng": 3.96641,
    "timestamp": "2015-07-25T05:04:46+00:00"
  },
  {
    "lat": 49.74921,
    "lng": 3.98216,
    "timestamp": "2015-07-25T05:09:36+00:00"
  },
  {
    "lat": 49.7372,
    "lng": 3.99658,
    "timestamp": "2015-07-25T05:14:41+00:00"
  },
  {
    "lat": 49.72791,
    "lng": 4.00984,
    "timestamp": "2015-07-25T05:19:36+00:00"
  },
  {
    "lat": 49.71419,
    "lng": 4.01894,
    "timestamp": "2015-07-25T05:24:35+00:00"
  },
  {
    "lat": 49.69557,
    "lng": 4.01559,
    "timestamp": "2015-07-25T05:29:39+00:00"
  },
  {
    "lat": 49.69538,
    "lng": 4.01507,
    "timestamp": "2015-07-25T05:34:41+00:00"
  },
  {
    "lat": 49.69547,
    "lng": 4.01542,
    "timestamp": "2015-07-25T05:41:36+00:00"
  },
  {
    "lat": 49.69573,
    "lng": 4.01525,
    "timestamp": "2015-07-25T05:46:36+00:00"
  },
  {
    "lat": 49.68938,
    "lng": 4.0107,
    "timestamp": "2015-07-25T05:51:36+00:00"
  },
  {
    "lat": 49.68306,
    "lng": 4.01098,
    "timestamp": "2015-07-25T05:54:38+00:00"
  },
  {
    "lat": 49.66774,
    "lng": 4.02014,
    "timestamp": "2015-07-25T05:59:40+00:00"
  },
  {
    "lat": 49.65218,
    "lng": 4.02522,
    "timestamp": "2015-07-25T06:04:40+00:00"
  },
  {
    "lat": 49.63458,
    "lng": 4.02162,
    "timestamp": "2015-07-25T06:09:40+00:00"
  },
  {
    "lat": 49.62088,
    "lng": 4.0275,
    "timestamp": "2015-07-25T06:14:35+00:00"
  },
  {
    "lat": 49.60191,
    "lng": 4.04503,
    "timestamp": "2015-07-25T06:20:34+00:00"
  },
  {
    "lat": 49.59076,
    "lng": 4.05277,
    "timestamp": "2015-07-25T06:24:39+00:00"
  },
  {
    "lat": 49.57235,
    "lng": 4.05503,
    "timestamp": "2015-07-25T06:29:40+00:00"
  },
  {
    "lat": 49.55463,
    "lng": 4.05117,
    "timestamp": "2015-07-25T06:34:40+00:00"
  },
  {
    "lat": 49.55204,
    "lng": 4.0505,
    "timestamp": "2015-07-25T06:39:39+00:00"
  },
  {
    "lat": 49.53467,
    "lng": 4.04619,
    "timestamp": "2015-07-25T06:45:35+00:00"
  },
  {
    "lat": 49.52176,
    "lng": 4.04335,
    "timestamp": "2015-07-25T06:49:44+00:00"
  },
  {
    "lat": 49.50763,
    "lng": 4.04044,
    "timestamp": "2015-07-25T06:55:06+00:00"
  },
  {
    "lat": 49.49109,
    "lng": 4.04108,
    "timestamp": "2015-07-25T06:59:45+00:00"
  },
  {
    "lat": 49.47375,
    "lng": 4.04155,
    "timestamp": "2015-07-25T07:04:48+00:00"
  },
  {
    "lat": 49.45622,
    "lng": 4.04003,
    "timestamp": "2015-07-25T07:09:52+00:00"
  },
  {
    "lat": 49.43752,
    "lng": 4.03398,
    "timestamp": "2015-07-25T07:14:52+00:00"
  },
  {
    "lat": 49.42339,
    "lng": 4.04308,
    "timestamp": "2015-07-25T07:19:52+00:00"
  },
  {
    "lat": 49.4095,
    "lng": 4.04138,
    "timestamp": "2015-07-25T07:24:52+00:00"
  },
  {
    "lat": 49.39238,
    "lng": 4.03941,
    "timestamp": "2015-07-25T07:29:52+00:00"
  },
  {
    "lat": 49.37513,
    "lng": 4.03747,
    "timestamp": "2015-07-25T07:34:56+00:00"
  },
  {
    "lat": 49.36127,
    "lng": 4.03593,
    "timestamp": "2015-07-25T07:39:56+00:00"
  },
  {
    "lat": 49.34795,
    "lng": 4.03432,
    "timestamp": "2015-07-25T07:44:54+00:00"
  },
  {
    "lat": 49.33228,
    "lng": 4.03263,
    "timestamp": "2015-07-25T07:49:56+00:00"
  },
  {
    "lat": 49.31131,
    "lng": 4.0231,
    "timestamp": "2015-07-25T07:56:55+00:00"
  },
  {
    "lat": 49.30122,
    "lng": 4.02808,
    "timestamp": "2015-07-25T07:59:55+00:00"
  },
  {
    "lat": 49.28823,
    "lng": 4.02773,
    "timestamp": "2015-07-25T08:04:57+00:00"
  },
  {
    "lat": 49.28815,
    "lng": 4.02769,
    "timestamp": "2015-07-25T08:09:56+00:00"
  },
  {
    "lat": 49.27684,
    "lng": 4.0269,
    "timestamp": "2015-07-25T08:14:58+00:00"
  },
  {
    "lat": 49.26626,
    "lng": 4.03838,
    "timestamp": "2015-07-25T08:20:03+00:00"
  },
  {
    "lat": 49.25579,
    "lng": 4.04616,
    "timestamp": "2015-07-25T08:25:06+00:00"
  },
  {
    "lat": 49.25201,
    "lng": 4.04479,
    "timestamp": "2015-07-25T08:30:06+00:00"
  },
  {
    "lat": 49.24447,
    "lng": 4.04891,
    "timestamp": "2015-07-25T08:35:06+00:00"
  },
  {
    "lat": 49.24008,
    "lng": 4.05771,
    "timestamp": "2015-07-25T08:40:04+00:00"
  },
  {
    "lat": 49.23654,
    "lng": 4.06979,
    "timestamp": "2015-07-25T08:45:06+00:00"
  },
  {
    "lat": 49.22621,
    "lng": 4.10369,
    "timestamp": "2015-07-25T08:50:27+00:00"
  },
  {
    "lat": 49.22429,
    "lng": 4.1094,
    "timestamp": "2015-07-25T08:55:00+00:00"
  },
  {
    "lat": 49.22425,
    "lng": 4.10949,
    "timestamp": "2015-07-25T09:00:00+00:00"
  },
  {
    "lat": 49.21828,
    "lng": 4.1288,
    "timestamp": "2015-07-25T09:05:00+00:00"
  },
  {
    "lat": 49.20336,
    "lng": 4.15214,
    "timestamp": "2015-07-25T09:10:09+00:00"
  },
  {
    "lat": 49.18727,
    "lng": 4.15772,
    "timestamp": "2015-07-25T09:15:09+00:00"
  },
  {
    "lat": 49.17242,
    "lng": 4.17274,
    "timestamp": "2015-07-25T09:20:09+00:00"
  },
  {
    "lat": 49.16077,
    "lng": 4.20051,
    "timestamp": "2015-07-25T09:25:05+00:00"
  },
  {
    "lat": 49.14349,
    "lng": 4.2201,
    "timestamp": "2015-07-25T09:30:08+00:00"
  },
  {
    "lat": 49.12677,
    "lng": 4.23941,
    "timestamp": "2015-07-25T09:35:03+00:00"
  },
  {
    "lat": 49.11149,
    "lng": 4.25555,
    "timestamp": "2015-07-25T09:40:03+00:00"
  },
  {
    "lat": 49.0935,
    "lng": 4.27134,
    "timestamp": "2015-07-25T09:45:03+00:00"
  },
  {
    "lat": 49.07764,
    "lng": 4.28499,
    "timestamp": "2015-07-25T09:50:01+00:00"
  },
  {
    "lat": 49.05888,
    "lng": 4.29791,
    "timestamp": "2015-07-25T09:55:02+00:00"
  },
  {
    "lat": 49.03358,
    "lng": 4.3196,
    "timestamp": "2015-07-25T09:59:57+00:00"
  },
  {
    "lat": 49.02465,
    "lng": 4.32552,
    "timestamp": "2015-07-25T10:04:57+00:00"
  },
  {
    "lat": 49.00843,
    "lng": 4.33196,
    "timestamp": "2015-07-25T10:09:57+00:00"
  }
]