[
  {
    "lat": 50.68325,
    "timestamp": "2015-07-24T23:02:05+00:00",
    "lng": 3.85991
  },
  {
    "lat": 50.67348,
    "timestamp": "2015-07-24T23:05:45+00:00",
    "lng": 3.86775
  },
  {
    "lat": 50.65714,
    "timestamp": "2015-07-24T23:10:42+00:00",
    "lng": 3.8733
  },
  {
    "lat": 50.6446,
    "timestamp": "2015-07-24T23:15:42+00:00",
    "lng": 3.86809
  },
  {
    "lat": 50.63029,
    "timestamp": "2015-07-24T23:20:40+00:00",
    "lng": 3.86152
  },
  {
    "lat": 50.61679,
    "timestamp": "2015-07-24T23:25:40+00:00",
    "lng": 3.85135
  },
  {
    "lat": 50.60386,
    "timestamp": "2015-07-24T23:30:37+00:00",
    "lng": 3.83676
  },
  {
    "lat": 50.59304,
    "timestamp": "2015-07-24T23:35:37+00:00",
    "lng": 3.82607
  },
  {
    "lat": 50.58377,
    "timestamp": "2015-07-24T23:40:34+00:00",
    "lng": 3.80597
  },
  {
    "lat": 50.56843,
    "timestamp": "2015-07-24T23:45:34+00:00",
    "lng": 3.8061
  }
]